ARaza/init.py
ARaza-0.1.dist-info/METADATA
ARaza-0.1.dist-info/WHEEL
ARaza-0.1.dist-info/top_level.txt
ARaza-0.1.dist-info/RECORD
