Metadata-Version: 2.1
Name: ARaza
Version: 0.1
Summary: this is a package
Author: Sir Qasim and Atiq Raza
License: UNKNOWN
Platform: UNKNOWN
